pytest_testrail/__init__.py
pytest_testrail/config_manager.py
pytest_testrail/controller.py
pytest_testrail/converters.py
pytest_testrail/logger.py
pytest_testrail/plugin.py
pytest_testrail/result_item.py
pytest_testrail/results.py
pytest_testrail/status.py
pytest_testrail/store.py
pytest_testrail/testrail_api_client.py
pytest_testrail2-1.1.0.dist-info/LICENSE
pytest_testrail2-1.1.0.dist-info/METADATA
pytest_testrail2-1.1.0.dist-info/WHEEL
pytest_testrail2-1.1.0.dist-info/entry_points.txt
pytest_testrail2-1.1.0.dist-info/top_level.txt
pytest_testrail2-1.1.0.dist-info/RECORD
