Metadata-Version: 2.1
Name: pytest-testrail2
Version: 1.1.0
Summary: A pytest plugin to upload results to TestRail.
Home-page: http://github.com/jsfehler/pytest-testrail2/
Author: Joshua Fehler
Classifier: Programming Language :: Python :: 3.7
Classifier: Programming Language :: Python :: 3.8
Classifier: Programming Language :: Python :: 3.9
Classifier: Programming Language :: Python :: 3.10
Classifier: Programming Language :: Python :: 3.11
Classifier: License :: OSI Approved :: MIT License
Classifier: Operating System :: OS Independent
License-File: LICENSE
Requires-Dist: pytest (<8.0,>=7.2.0)
Requires-Dist: requests (<3.0,>=2.20.0)
Requires-Dist: inori (<1.0,>=0.0.8)
Requires-Dist: filelock (<4.0,>=3.6.0)
